<?xml version="1.0" encoding="utf-8"?>
<resources>
    <plurals name="pages_left">
        <item quantity="one">Cetere %1$d paĝo</item>
        <item quantity="other">Cetere %1$d paĝoj</item>
    </plurals>

    <plurals name="remove_n_chapters">
        <item quantity="one">Forigi %1$d elŝutitan ĉapitron\?</item>
        <item quantity="other">Forigi %1$d elŝutitajn ĉapitrojn\?</item>
    </plurals>

    <plurals name="chapters_plural">
        <item quantity="one">1 ĉapitro</item>
        <item quantity="other">%1$s ĉapitroj</item>
    </plurals>

    <plurals name="category_plural">
        <item quantity="one">%d kategorio%d kategorioj</item>
        <item quantity="other"/>
    </plurals>

    <plurals name="restore_completed_message">
        <item quantity="one">Farita en %1$s kun %2$s eraro</item>
        <item quantity="other">Farita en %1$s kun %2$s eraroj</item>
    </plurals>

    <plurals name="missing_chapters_warning">
        <item quantity="one">Mankas 1 ĉapitron</item>
        <item quantity="other">Mankas %d ĉapitrojn</item>
    </plurals>

    <plurals name="after_minutes">
        <item quantity="one">Post 1 minutoPost %1$s minutoj</item>
        <item quantity="other"/>
    </plurals>

    <plurals name="for_n_titles">
        <item quantity="one">Por 1 titoloPor %d titoloj</item>
        <item quantity="other"/>
    </plurals>
</resources>
